README.md
setup.py
ufterm/__init__.py
ufterm/constant.py
ufterm/exception.py
ufterm/gui.py
ufterm/register.py
ufterm/terminal.py
ufterm/utils.py
ufterm.egg-info/PKG-INFO
ufterm.egg-info/SOURCES.txt
ufterm.egg-info/dependency_links.txt
ufterm.egg-info/top_level.txt