Metadata-Version: 2.1
Name: ufterm
Version: 0.0.2
Summary: Simple Friendly terminal.py interface
Home-page: https://gitlab.com/olive007/ufterm
Author: SECRET Olivier
Author-email: pypi-package-ufterm@devo.live
License: UNKNOWN
Platform: UNKNOWN
Classifier: Programming Language :: Python :: 3
Classifier: License :: OSI Approved :: GNU Lesser General Public License v3 or later (LGPLv3+)
Classifier: Operating System :: OS Independent
